{
    "character": {
        "name": "Hero",
        "attributes": {
            "Strength": 9,
            "Agility": 4,
            "Charisma": 8,
            "Intelligence": 4
        },
        "skills": {
            "Running": 4,
            "Riding": 6,
            "Management": 9,
            "Eloquence": 1,
            "Gathering": 4
        },
        "inventory": {
            "Apple": {
                "quantity": 88,
                "weight": 0.5,
                "value": 5
            },
            "Blueberry": {
                "quantity": 15,
                "weight": 0.1,
                "value": 2
            },
            "Mulberry": {
                "quantity": 20,
                "weight": 0.2,
                "value": 3
            },
            "Sword": {
                "quantity": 1,
                "weight": 5.0,
                "value": 100
            }
        }
    },
    "companions": [
        {
            "id": "fab94e40-1c39-4fc7-b822-ba648728fd7d",
            "name": "Diana",
            "attributes": {
                "Strength": 2,
                "Agility": 5,
                "Charisma": 5,
                "Intelligence": 6
            },
            "skills": {
                "Running": 8,
                "Riding": 1,
                "Management": 7,
                "Eloquence": 5,
                "Gathering": 2
            }
        },
        {
            "id": "b70eaa4a-354b-4bf1-bd15-c312812a4856",
            "name": "Charlie",
            "attributes": {
                "Strength": 5,
                "Agility": 10,
                "Charisma": 9,
                "Intelligence": 1
            },
            "skills": {
                "Running": 3,
                "Riding": 7,
                "Management": 7,
                "Eloquence": 2,
                "Gathering": 6
            }
        },
        {
            "id": "790cd02a-93c5-403a-8ed7-23f6943c694b",
            "name": "Bob",
            "attributes": {
                "Strength": 10,
                "Agility": 10,
                "Charisma": 4,
                "Intelligence": 7
            },
            "skills": {
                "Running": 1,
                "Riding": 8,
                "Management": 1,
                "Eloquence": 3,
                "Gathering": 3
            }
        },
        {
            "id": "9387eaac-42fa-4ee7-8742-376c9105034f",
            "name": "Diana",
            "attributes": {
                "Strength": 9,
                "Agility": 7,
                "Charisma": 6,
                "Intelligence": 1
            },
            "skills": {
                "Running": 8,
                "Riding": 1,
                "Management": 6,
                "Eloquence": 6,
                "Gathering": 2
            }
        },
        {
            "id": "75623dbc-d171-4a3c-8dbb-8afe99b9417e",
            "name": "Diana",
            "attributes": {
                "Strength": 2,
                "Agility": 1,
                "Charisma": 2,
                "Intelligence": 10
            },
            "skills": {
                "Running": 7,
                "Riding": 1,
                "Management": 4,
                "Eloquence": 2,
                "Gathering": 2
            }
        },
        {
            "id": "aeb7c871-f288-49d4-892d-0ebd95755793",
            "name": "Diana",
            "attributes": {
                "Strength": 1,
                "Agility": 3,
                "Charisma": 10,
                "Intelligence": 10
            },
            "skills": {
                "Running": 4,
                "Riding": 3,
                "Management": 1,
                "Eloquence": 9,
                "Gathering": 7
            }
        },
        {
            "id": "046fd3dc-4e9b-497e-a4f9-c530469b7f8e",
            "name": "Bob",
            "attributes": {
                "Strength": 5,
                "Agility": 3,
                "Charisma": 4,
                "Intelligence": 1
            },
            "skills": {
                "Running": 3,
                "Riding": 8,
                "Management": 2,
                "Eloquence": 9,
                "Gathering": 8
            }
        },
        {
            "id": "366cc6b9-33f8-4585-9d05-b0cbba036936",
            "name": "Diana",
            "attributes": {
                "Strength": 5,
                "Agility": 3,
                "Charisma": 8,
                "Intelligence": 5
            },
            "skills": {
                "Running": 5,
                "Riding": 8,
                "Management": 4,
                "Eloquence": 10,
                "Gathering": 5
            }
        },
        {
            "id": "44a85ed7-6ffc-46ac-b891-21d631f31efb",
            "name": "Charlie",
            "attributes": {
                "Strength": 6,
                "Agility": 9,
                "Charisma": 6,
                "Intelligence": 4
            },
            "skills": {
                "Running": 6,
                "Riding": 4,
                "Management": 9,
                "Eloquence": 8,
                "Gathering": 1
            }
        },
        {
            "id": "a1235249-ddd5-42de-b960-035f198c68a3",
            "name": "Alice",
            "attributes": {
                "Strength": 7,
                "Agility": 8,
                "Charisma": 8,
                "Intelligence": 5
            },
            "skills": {
                "Running": 3,
                "Riding": 6,
                "Management": 5,
                "Eloquence": 8,
                "Gathering": 10
            }
        },
        {
            "id": "ded21683-7eca-4a64-92b8-aa521858abbe",
            "name": "Bob",
            "attributes": {
                "Strength": 6,
                "Agility": 7,
                "Charisma": 6,
                "Intelligence": 2
            },
            "skills": {
                "Running": 10,
                "Riding": 1,
                "Management": 4,
                "Eloquence": 1,
                "Gathering": 10
            }
        },
        {
            "id": "1df3bbf6-01ac-4a97-a3ea-37cd413e6872",
            "name": "Bob",
            "attributes": {
                "Strength": 6,
                "Agility": 2,
                "Charisma": 4,
                "Intelligence": 4
            },
            "skills": {
                "Running": 6,
                "Riding": 1,
                "Management": 3,
                "Eloquence": 10,
                "Gathering": 8
            }
        },
        {
            "id": "c770eaff-f68d-4e77-98d1-0157fd032a95",
            "name": "Edward",
            "attributes": {
                "Strength": 6,
                "Agility": 7,
                "Charisma": 3,
                "Intelligence": 7
            },
            "skills": {
                "Running": 9,
                "Riding": 9,
                "Management": 2,
                "Eloquence": 9,
                "Gathering": 6
            }
        },
        {
            "id": "033be0f8-d0f9-45f2-98fb-1ae40a4d34a4",
            "name": "Edward",
            "attributes": {
                "Strength": 7,
                "Agility": 7,
                "Charisma": 9,
                "Intelligence": 4
            },
            "skills": {
                "Running": 3,
                "Riding": 6,
                "Management": 7,
                "Eloquence": 8,
                "Gathering": 1
            }
        },
        {
            "id": "c6b1e3a6-5d27-4e9d-a1a0-6edadd0758fe",
            "name": "Alice",
            "attributes": {
                "Strength": 9,
                "Agility": 5,
                "Charisma": 10,
                "Intelligence": 10
            },
            "skills": {
                "Running": 1,
                "Riding": 8,
                "Management": 3,
                "Eloquence": 10,
                "Gathering": 2
            }
        }
    ],
    "state": {
        "hunger": 69.59999999999957,
        "thirst": 84.80000000000086,
        "fatigue": 24.0,
        "mood": 84.80000000000086,
        "is_traveling": true,
        "day_count": 1,
        "distance": 12160.0,
        "game_time": "02:32"
    },
    "log": [
        "You found an apple!",
        "You met Diana!",
        "You found an apple!",
        "You found an apple!",
        "You found an apple!",
        "You found an apple!",
        "You met Charlie!",
        "You met Bob!",
        "You found an apple!",
        "You found an apple!",
        "You met Diana!",
        "You found an apple!",
        "You met Diana!",
        "You found an apple!",
        "You found an apple!",
        "You found an apple!",
        "You met Diana!",
        "You found an apple!",
        "You found an apple!",
        "You found an apple!",
        "You met Bob!",
        "You found an apple!",
        "You found an apple!",
        "You found an apple!",
        "You found an apple!",
        "You found an apple!",
        "You found an apple!",
        "You found an apple!",
        "You found an apple!",
        "You found an apple!",
        "You found an apple!",
        "You found an apple!",
        "You found an apple!",
        "You found an apple!",
        "You found an apple!",
        "You found an apple!",
        "You found an apple!",
        "You found an apple!",
        "You found an apple!",
        "You found an apple!",
        "You met Diana!",
        "You found an apple!",
        "You found an apple!",
        "You met Charlie!",
        "You found an apple!",
        "You found an apple!",
        "You found an apple!",
        "You found an apple!",
        "You found an apple!",
        "You met Alice!",
        "You found an apple!",
        "You found an apple!",
        "You met Bob!",
        "You found an apple!",
        "You found an apple!",
        "You found an apple!",
        "You found an apple!",
        "You found an apple!",
        "You found an apple!",
        "You found an apple!",
        "You found an apple!",
        "You found an apple!",
        "You found an apple!",
        "You met Bob!",
        "You met Edward!",
        "You found an apple!",
        "You found an apple!",
        "You found an apple!",
        "You found an apple!",
        "You found an apple!",
        "You found an apple!",
        "You found an apple!",
        "You found an apple!",
        "You found an apple!",
        "You found an apple!",
        "You found an apple!",
        "You found an apple!",
        "You found an apple!",
        "You found an apple!",
        "You found an apple!",
        "You met Edward!",
        "You found an apple!",
        "You found an apple!",
        "You found an apple!",
        "You found an apple!",
        "You found an apple!",
        "You met Alice!",
        "You found an apple!",
        "You found an apple!",
        "You found an apple!",
        "You found an apple!",
        "You found an apple!",
        "You found an apple!"
    ]
}